mutwo/abjad_converters/__init__.py
mutwo/abjad_converters/configurations.py
mutwo/abjad_converters/process_container_routines.py
mutwo/abjad_converters/events/__init__.py
mutwo/abjad_converters/events/building.py
mutwo/abjad_converters/events/quantization.py
mutwo/abjad_converters/parameters/__init__.py
mutwo/abjad_converters/parameters/heji.py
mutwo/abjad_converters/parameters/lyrics.py
mutwo/abjad_converters/parameters/pitches.py
mutwo/abjad_converters/parameters/tempos.py
mutwo/abjad_converters/parameters/volumes.py
mutwo/abjad_parameters/__init__.py
mutwo/abjad_parameters/abc.py
mutwo/abjad_parameters/attachments.py
mutwo/abjad_parameters/configurations.py
mutwo/abjad_parameters/constants.py
mutwo_third_party/abjad/__init__.py
mutwo.ext_abjad-0.10.0.dist-info/LICENSE
mutwo.ext_abjad-0.10.0.dist-info/METADATA
mutwo.ext_abjad-0.10.0.dist-info/WHEEL
mutwo.ext_abjad-0.10.0.dist-info/top_level.txt
mutwo.ext_abjad-0.10.0.dist-info/RECORD
