Metadata-Version: 2.1
Name: mutwo.ext-abjad
Version: 0.10.0
Summary: abjad extension for event based framework mutwo
Home-page: https://github.com/mutwo-org/mutwo.ext-abjad
Author: Levin Eric Zimmermann
Author-email: levin.eric.zimmermann@posteo.eu
License: GPL
Project-URL: Documentation, https://mutwo.readthedocs.io/en/latest/
Requires-Python: >=3.9, <4
License-File: LICENSE
Requires-Dist: mutwo.ext-core (<0.60.0,>=0.59.0)
Requires-Dist: mutwo.ext-music (<0.17.0,>=0.16.0)
Requires-Dist: abjad (<3.5.0,>=3.4.0)
Requires-Dist: abjad-ext-nauert (<3.5.0,>=3.4.0)
Provides-Extra: testing
Requires-Dist: nose ; extra == 'testing'
Requires-Dist: coveralls ; extra == 'testing'
Requires-Dist: pillow (<9.0.0,>=8.2.0) ; extra == 'testing'
Requires-Dist: mutwo.ext-ekmelily (<0.7.0,>=0.6.2) ; extra == 'testing'
